tglib/__init__.py
tglib/api.py
tglib/client.py
tglib/constants.py
tglib/logger.py
tglib/types.py
tglib/update_manager.py
tglib/utils.py
tglib-1.3.4.dist-info/LICENSE
tglib-1.3.4.dist-info/METADATA
tglib-1.3.4.dist-info/WHEEL
tglib-1.3.4.dist-info/top_level.txt
tglib-1.3.4.dist-info/RECORD
