Metadata-Version: 2.1
Name: tglib
Version: 1.3.4
Author: unixtux
License: GNU GENERAL PUBLIC LICENSE
Project-URL: Repository, https://github.com/unixtux/tglib
Requires-Python: >=3.8
License-File: LICENSE
Requires-Dist: aiohttp >=3.9.1
Requires-Dist: certifi >=2023.11.17
Requires-Dist: ujson >=5.9.0
